Workbook

Sheet Cost Breakdown
A3: COST BREAKDOWN
A4: Services Offered | B4: Breakdown of Service | C4: Solo/Startup Fee (Revenue under $250K/year) | D4: Small Bus. Fee (Revenue $250k-$1M/year) | E4: Mid-Market Fee (Revenue $1M–$5M/year) | F4: Considerations | H4: Revenue Model
A5: Tier 1- Financial Clarity (Base Layer) | H5: Type | I5: Description | J5: Price Range
A6: Bookkeeping | C6: $500–$800/mo | D6: $900 – $1,500 / mo | E6: $1,800 – $2,800 / mo | H6: Recurring Retainers | I6: Monthly accounting + dashboard package | J6: $800–$3,000/month
A7: Month-end close + Reconcillations + Financial Statement Preperation (Consulting aspect varies by company size) | B7: Identify anomalies. For larger businesses do GAAP reporting, variance analysis, management packages | C7: $500 – $800 / mo | D7: $900 – $1,500 / mo | E7: $1,800 – $2,800 / mo | F7: Set limit on accruals in contract | H7: Projects | I7: System setups, forecasts, automation builds | J7: $1,500–$7,000/project
A8: Payroll +1099 contractor setup | C8: $150-$300 /mo | D8: $350 – $600 / mo | E8: $700 – $1,200 / mo | H8: Intensives | I8: 90-minute paid strategy calls | J8: $250–$500/session
A9: Cleanup Projects or accounting migrations | C9: $750-$1,500 project | D9: $2,000–$3,000 project | E9: $3,500–$5,000 project | H9: High-End Consulting | I9: Fractional CFO or long-term strategy | J9: $3,000–$8,000/month
A10: Accounting System Overhaul | B10: Fixing messy books in 30 days | C10: $1,000 – $2,000 project | D10: $2,500 – $3,500 project | E10: $4,000 – $5,000 project
A11: Monthly Review Call | C11: $100-$150 /mo | D11: $150-$200 /mo | E11: $150-$200 /mo
A12: Tier 2- Insight and Optimization (Mid Layer)
A13: KPI Dashboard Design (Power BI, Excel Power Query) | C13: $1,200 – $2,000 one-time (+ $250 / mo maintenance) | D13: $2,500 – $3,000 project (+ $300 / mo maintenance) | E13: $4,000 – $7,000 project (+ $500 / mo maintenance)
A14: Monthly Performance Reviews (Revenue, COGS, Cashflow) | C14: $800 – $1,200 / mo | D14: $1,500 – $2,500 / mo | E14: $3,000 – $4,000 / mo
A15: Cost and Profitability analysis | C15: $1,000 – $1,500 project | D15: $2,000 – $3,000 project | E15: $3,500 – $5,000 proje
A16: Budgeting and Forecast Templates | C16: $800 – $1,200 project | D16: $1,500 – $2,500 project | E16: $3,000 – $4,500 proje
A17: Workflow Automation (Bank Feeds, Reporting Pipelines) | C17: $1,000 – $2,000 setup | D17: $2,000 – $3,000 setup | E17: $3,500 – $5,000 s
A18: Quarterly Business Helath Check Packages | C18: $400 – $600 / quarter | D18: $800 – $1,200 / quarter | E18: $1,500 – $2,500 / quarter
A19: Profit Optimization Report | B19: Custom Report Identifying 5 ways to increase profit margin using existing data | C19: $400 – $700 one-time | D19: $800 – $1,000 one-time | E19: $1,200 – $1,500 one-time
A20: Tier 3-Strategic Growth Consulting (High-End Layer)
A21: Fractional CFO or Outsourced Controller | C21: $1,200 – $2,000 / mo | D21: $2,500 – $5,000 / mo | E21: $6,000 – $9,000 / mo | F21: Not sure about offering yet
A22: Strategic planning & cash flow forecasting | C22: $1,000 – $2,000 project | D22: $2,500 – $3,500 project | E22: $4,000 – $6,000 project
A23: Pricing & margin strategy | C23: $800 – $1,200 project | D23: $1,800 – $2,500 project | E23: $3,000 – $4,000 project
A24: M&A preparation (valuation, due diligence support) | C24: $2,000 – $3,000 project | D24: $3,500 – $5,000 project | E24: $6,000 – $8,000 project | F24: Not sure about offering yet
A25: Financial model development (3-5 year projections) | C25: $2,000 – $3,000 project | D25: $3,500 – $5,000 project | E25: $5,000 – $7,000 project | F25: Not sure about offering yet
A26: Performance strategy consulting (OKRs, KPI alignment) | C26: $1,500 – $2,500 package | D26: $2,500 – $4,000 package | E26: $4,000 – $6,000 package
A27: Financial Strategy Intensive | B27: 90-minute workshop analyzing business goals, bottlenecks, and systems (great for onboarding new consulting clients) | C27: $250 – $400 session | D27: $400 – $600 session | E27: $600 – $900 session | F27: Not sure about offering yet
A28: Tier 4: Business Reinvention (Long-term Vision Layer)
A29: AI-driven forecasting implementation (Power BI + ChatGPT or Gemini integration) | C29: $3,000 – $5,000 project | D29: $6,000 – $10,000 project | E29: $10,000 – $15,000 project
A30: Digital transformation audits (process efficiency + automation mapping) | C30: $2,500 – $4,000 project | D30: $5,000 – $8,000 project | E30: $8,000 – $12,000 project
A31: Sustainability & ESG metrics tracking for mid-market firms | C31: $2,000 – $3,000 setup (+ $500 / mo maintenance) | D31: $4,000 – $6,000 setup (+ $800 / mo maintenance) | E31: $6,000 – $9,000 setup (+ $1,200 / mo maintenance)
A32: Business turnaround strategy packages | C32: $3,000 – $5,000 project | D32: $6,000 – $9,000 project | E32: $10,000 – $15,000 project
A33: Strategic workshops for founders (vision alignment, growth modeling) | C33: $500 – $800 session | D33: $1,000 – $1,500 session | E33: $2,000 – $3,000 session | F33: Not sure about offering yet

Sheet Calculator
A1: PRICING CALCULATOR
D2: Settings
D3: Client Size | E3: Price Point
D4: Solo/Startup | E4: High
A5: Client Size (effective) | B5: =D4 -> Solo/Startup
A6: Price Point (effective) | B6: =E4 -> High
A8: Services and their Associated Fees | P8: Calculation
A9: Select | B9: Qty | C9: Include_Maintenance | D9: Tier | E9: Service | F9: Billing | G9: Solo_Low | H9: Solo_High | I9: Solo_Maint | J9: Small_Low | K9: Small_High | L9: Small_Maint | M9: Mid_Low | N9: Mid_High | O9: Mid_Maint | P9: Low | Q9: High | R9: Value Selected | S9: Subtotal | T9: Timing
A10: TRUE | B10: 1 | C10: FALSE | D10: Tier 1 – Financial Clarity (Base Layer) | E10: Bookkeeping | F10: Monthly | G10: 500 | H10: 800 | J10: 900 | K10: 1500 | M10: 1800 | N10: 2800 | P10: =IF($B$5="Solo/Startup", G10, IF($B$5="Small Business", J10, M10)) -> 500 | Q10: =IF($B$5="Solo/Startup", H10, IF($B$5="Small Business", K10, N10)) -> 800 | R10: =IF($B$6="Low", P10, IF($B$6="High", Q10, AVERAGE(P10,Q10))) -> 800 | S10: =IF(A10, B10*R10, 0) -> 800 | T10: =IF(F10="Monthly","Monthly","One-time/Non-monthly") -> Monthly
A11: TRUE | B11: 1 | C11: FALSE | D11: Tier 1 – Financial Clarity (Base Layer) | E11: Month-end close + Reconciliations + Financial Statement Prep | F11: Monthly | G11: 500 | H11: 800 | J11: 900 | K11: 1500 | M11: 1800 | N11: 2800 | P11: =IF($B$5="Solo/Startup", G11, IF($B$5="Small Business", J11, M11)) -> 500 | Q11: =IF($B$5="Solo/Startup", H11, IF($B$5="Small Business", K11, N11)) -> 800 | R11: =IF($B$6="Low", P11, IF($B$6="High", Q11, AVERAGE(P11,Q11))) -> 800 | S11: =IF(A11, B11*R11, 0) -> 800 | T11: =IF(F11="Monthly","Monthly","One-time/Non-monthly") -> Monthly
A12: TRUE | B12: 1 | C12: FALSE | D12: Tier 1 – Financial Clarity (Base Layer) | E12: Payroll + 1099 contractor setup | F12: Monthly | G12: 150 | H12: 300 | J12: 350 | K12: 600 | M12: 700 | N12: 1200 | P12: =IF($B$5="Solo/Startup", G12, IF($B$5="Small Business", J12, M12)) -> 150 | Q12: =IF($B$5="Solo/Startup", H12, IF($B$5="Small Business", K12, N12)) -> 300 | R12: =IF($B$6="Low", P12, IF($B$6="High", Q12, AVERAGE(P12,Q12))) -> 300 | S12: =IF(A12, B12*R12, 0) -> 300 | T12: =IF(F12="Monthly","Monthly","One-time/Non-monthly") -> Monthly
A13: TRUE | B13: 1 | C13: FALSE | D13: Tier 1 – Financial Clarity (Base Layer) | E13: Cleanup Projects or accounting migrations | F13: Project | G13: 750 | H13: 1500 | J13: 2500 | K13: 3000 | M13: 3500 | N13: 5000 | P13: =IF($B$5="Solo/Startup", G13, IF($B$5="Small Business", J13, M13)) -> 750 | Q13: =IF($B$5="Solo/Startup", H13, IF($B$5="Small Business", K13, N13)) -> 1500 | R13: =IF($B$6="Low", P13, IF($B$6="High", Q13, AVERAGE(P13,Q13))) -> 1500 | S13: =IF(A13, B13*R13, 0) -> 1500 | T13: =IF(F13="Monthly","Monthly","One-time/Non-monthly") -> One-time/Non-monthly
A14: TRUE | B14: 1 | C14: FALSE | D14: Tier 1 – Financial Clarity (Base Layer) | E14: Accounting System Overhaul | F14: Project | G14: 1000 | H14: 2000 | J14: 2500 | K14: 3500 | M14: 4000 | N14: 5000 | P14: =IF($B$5="Solo/Startup", G14, IF($B$5="Small Business", J14, M14)) -> 1000 | Q14: =IF($B$5="Solo/Startup", H14, IF($B$5="Small Business", K14, N14)) -> 2000 | R14: =IF($B$6="Low", P14, IF($B$6="High", Q14, AVERAGE(P14,Q14))) -> 2000 | S14: =IF(A14, B14*R14, 0) -> 2000 | T14: =IF(F14="Monthly","Monthly","One-time/Non-monthly") -> One-time/Non-monthly
A15: FALSE | B15: 1 | C15: FALSE | D15: Tier 1 – Financial Clarity (Base Layer) | E15: Monthly Review Call | F15: Monthly | G15: 100 | H15: 150 | J15: 150 | K15: 200 | M15: 150 | N15: 200 | P15: =IF($B$5="Solo/Startup", G15, IF($B$5="Small Business", J15, M15)) -> 100 | Q15: =IF($B$5="Solo/Startup", H15, IF($B$5="Small Business", K15, N15)) -> 150 | R15: =IF($B$6="Low", P15, IF($B$6="High", Q15, AVERAGE(P15,Q15))) -> 150 | S15: =IF(A15, B15*R15, 0) -> 0 | T15: =IF(F15="Monthly","Monthly","One-time/Non-monthly") -> Monthly
A16: TRUE | B16: 1 | C16: TRUE | D16: Tier 2 – Insight & Optimization (Mid Layer) | E16: KPI Dashboard Design (Power BI, Excel, Power Query) | F16: One-time | G16: 1200 | H16: 2000 | I16: 250 | J16: 2500 | K16: 3000 | L16: 300 | M16: 4000 | N16: 7000 | O16: 500 | P16: =IF($B$5="Solo/Startup", G16, IF($B$5="Small Business", J16, M16)) -> 1200 | Q16: =IF($B$5="Solo/Startup", H16, IF($B$5="Small Business", K16, N16)) -> 2000 | R16: =IF($B$6="Low", P16, IF($B$6="High", Q16, AVERAGE(P16,Q16))) -> 2000 | S16: =IF(A16, B16*R16, 0) -> 2000 | T16: =IF(F16="Monthly","Monthly","One-time/Non-monthly") -> One-time/Non-monthly
A17: FALSE | B17: 1 | C17: FALSE | D17: Tier 2 – Insight & Optimization (Mid Layer) | E17: Monthly Performance Reviews (Revenue, COGS, Cashflow) | F17: Monthly | G17: 800 | H17: 1200 | J17: 1500 | K17: 2500 | M17: 3000 | N17: 4000 | P17: =IF($B$5="Solo/Startup", G17, IF($B$5="Small Business", J17, M17)) -> 800 | Q17: =IF($B$5="Solo/Startup", H17, IF($B$5="Small Business", K17, N17)) -> 1200 | R17: =IF($B$6="Low", P17, IF($B$6="High", Q17, AVERAGE(P17,Q17))) -> 1200 | S17: =IF(A17, B17*R17, 0) -> 0 | T17: =IF(F17="Monthly","Monthly","One-time/Non-monthly") -> Monthly
A18: FALSE | B18: 1 | C18: FALSE | D18: Tier 2 – Insight & Optimization (Mid Layer) | E18: Cost and Profitability analysis | F18: Project | G18: 1000 | H18: 1500 | J18: 2000 | K18: 3000 | M18: 3500 | N18: 5000 | P18: =IF($B$5="Solo/Startup", G18, IF($B$5="Small Business", J18, M18)) -> 1000 | Q18: =IF($B$5="Solo/Startup", H18, IF($B$5="Small Business", K18, N18)) -> 1500 | R18: =IF($B$6="Low", P18, IF($B$6="High", Q18, AVERAGE(P18,Q18))) -> 1500 | S18: =IF(A18, B18*R18, 0) -> 0 | T18: =IF(F18="Monthly","Monthly","One-time/Non-monthly") -> One-time/Non-monthly
A19: FALSE | B19: 1 | C19: FALSE | D19: Tier 2 – Insight & Optimization (Mid Layer) | E19: Budgeting and Forecast Templates | F19: Project | G19: 800 | H19: 1200 | J19: 1500 | K19: 2500 | M19: 3000 | N19: 4500 | P19: =IF($B$5="Solo/Startup", G19, IF($B$5="Small Business", J19, M19)) -> 800 | Q19: =IF($B$5="Solo/Startup", H19, IF($B$5="Small Business", K19, N19)) -> 1200 | R19: =IF($B$6="Low", P19, IF($B$6="High", Q19, AVERAGE(P19,Q19))) -> 1200 | S19: =IF(A19, B19*R19, 0) -> 0 | T19: =IF(F19="Monthly","Monthly","One-time/Non-monthly") -> One-time/Non-monthly
A20: FALSE | B20: 1 | C20: FALSE | D20: Tier 2 – Insight & Optimization (Mid Layer) | E20: Workflow Automation (Bank Feeds, Reporting Pipelines) | F20: Setup | G20: 1000 | H20: 2000 | J20: 2000 | K20: 3000 | M20: 3500 | N20: 5000 | P20: =IF($B$5="Solo/Startup", G20, IF($B$5="Small Business", J20, M20)) -> 1000 | Q20: =IF($B$5="Solo/Startup", H20, IF($B$5="Small Business", K20, N20)) -> 2000 | R20: =IF($B$6="Low", P20, IF($B$6="High", Q20, AVERAGE(P20,Q20))) -> 2000 | S20: =IF(A20, B20*R20, 0) -> 0 | T20: =IF(F20="Monthly","Monthly","One-time/Non-monthly") -> One-time/Non-monthly
A21: FALSE | B21: 1 | C21: FALSE | D21: Tier 2 – Insight & Optimization (Mid Layer) | E21: Quarterly Business Health Check Packages | F21: Quarterly | G21: 400 | H21: 600 | J21: 800 | K21: 1200 | M21: 1500 | N21: 2500 | P21: =IF($B$5="Solo/Startup", G21, IF($B$5="Small Business", J21, M21)) -> 400 | Q21: =IF($B$5="Solo/Startup", H21, IF($B$5="Small Business", K21, N21)) -> 600 | R21: =IF($B$6="Low", P21, IF($B$6="High", Q21, AVERAGE(P21,Q21))) -> 600 | S21: =IF(A21, B21*R21, 0) -> 0 | T21: =IF(F21="Monthly","Monthly","One-time/Non-monthly") -> One-time/Non-monthly
A22: FALSE | B22: 1 | C22: FALSE | D22: Tier 2 – Insight & Optimization (Mid Layer) | E22: Profit Optimization Report | F22: One-time | G22: 400 | H22: 700 | J22: 800 | K22: 1000 | M22: 1200 | N22: 1500 | P22: =IF($B$5="Solo/Startup", G22, IF($B$5="Small Business", J22, M22)) -> 400 | Q22: =IF($B$5="Solo/Startup", H22, IF($B$5="Small Business", K22, N22)) -> 700 | R22: =IF($B$6="Low", P22, IF($B$6="High", Q22, AVERAGE(P22,Q22))) -> 700 | S22: =IF(A22, B22*R22, 0) -> 0 | T22: =IF(F22="Monthly","Monthly","One-time/Non-monthly") -> One-time/Non-monthly
A23: FALSE | B23: 1 | C23: FALSE | D23: Tier 3 – Strategic Growth Consulting (High-End Layer) | E23: Fractional CFO or Outsourced Controller | F23: Monthly | G23: 1200 | H23: 2000 | J23: 2500 | K23: 5000 | M23: 6000 | N23: 9000 | P23: =IF($B$5="Solo/Startup", G23, IF($B$5="Small Business", J23, M23)) -> 1200 | Q23: =IF($B$5="Solo/Startup", H23, IF($B$5="Small Business", K23, N23)) -> 2000 | R23: =IF($B$6="Low", P23, IF($B$6="High", Q23, AVERAGE(P23,Q23))) -> 2000 | S23: =IF(A23, B23*R23, 0) -> 0 | T23: =IF(F23="Monthly","Monthly","One-time/Non-monthly") -> Monthly
A24: FALSE | B24: 1 | C24: FALSE | D24: Tier 3 – Strategic Growth Consulting (High-End Layer) | E24: Strategic planning & cash flow forecasting | F24: Project | G24: 1000 | H24: 2000 | J24: 2500 | K24: 3500 | M24: 4000 | N24: 6000 | P24: =IF($B$5="Solo/Startup", G24, IF($B$5="Small Business", J24, M24)) -> 1000 | Q24: =IF($B$5="Solo/Startup", H24, IF($B$5="Small Business", K24, N24)) -> 2000 | R24: =IF($B$6="Low", P24, IF($B$6="High", Q24, AVERAGE(P24,Q24))) -> 2000 | S24: =IF(A24, B24*R24, 0) -> 0 | T24: =IF(F24="Monthly","Monthly","One-time/Non-monthly") -> One-time/Non-monthly
A25: FALSE | B25: 1 | C25: FALSE | D25: Tier 3 – Strategic Growth Consulting (High-End Layer) | E25: Pricing & margin strategy | F25: Project | G25: 800 | H25: 1200 | J25: 1800 | K25: 2500 | M25: 3000 | N25: 4000 | P25: =IF($B$5="Solo/Startup", G25, IF($B$5="Small Business", J25, M25)) -> 800 | Q25: =IF($B$5="Solo/Startup", H25, IF($B$5="Small Business", K25, N25)) -> 1200 | R25: =IF($B$6="Low", P25, IF($B$6="High", Q25, AVERAGE(P25,Q25))) -> 1200 | S25: =IF(A25, B25*R25, 0) -> 0 | T25: =IF(F25="Monthly","Monthly","One-time/Non-monthly") -> One-time/Non-monthly
A26: FALSE | B26: 1 | C26: FALSE | D26: Tier 3 – Strategic Growth Consulting (High-End Layer) | E26: M&A preparation (valuation, due diligence support) | F26: Project | G26: 2000 | H26: 3000 | J26: 3500 | K26: 5000 | M26: 6000 | N26: 8000 | P26: =IF($B$5="Solo/Startup", G26, IF($B$5="Small Business", J26, M26)) -> 2000 | Q26: =IF($B$5="Solo/Startup", H26, IF($B$5="Small Business", K26, N26)) -> 3000 | R26: =IF($B$6="Low", P26, IF($B$6="High", Q26, AVERAGE(P26,Q26))) -> 3000 | S26: =IF(A26, B26*R26, 0) -> 0 | T26: =IF(F26="Monthly","Monthly","One-time/Non-monthly") -> One-time/Non-monthly
A27: FALSE | B27: 1 | C27: FALSE | D27: Tier 3 – Strategic Growth Consulting (High-End Layer) | E27: Financial model development (3–5 year projections) | F27: Project | G27: 2000 | H27: 3000 | J27: 3500 | K27: 5000 | M27: 5000 | N27: 7000 | P27: =IF($B$5="Solo/Startup", G27, IF($B$5="Small Business", J27, M27)) -> 2000 | Q27: =IF($B$5="Solo/Startup", H27, IF($B$5="Small Business", K27, N27)) -> 3000 | R27: =IF($B$6="Low", P27, IF($B$6="High", Q27, AVERAGE(P27,Q27))) -> 3000 | S27: =IF(A27, B27*R27, 0) -> 0 | T27: =IF(F27="Monthly","Monthly","One-time/Non-monthly") -> One-time/Non-monthly
A28: FALSE | B28: 1 | C28: FALSE | D28: Tier 3 – Strategic Growth Consulting (High-End Layer) | E28: Performance strategy consulting (OKRs, KPI alignment) | F28: Package | G28: 1500 | H28: 2500 | J28: 2500 | K28: 4000 | M28: 4000 | N28: 6000 | P28: =IF($B$5="Solo/Startup", G28, IF($B$5="Small Business", J28, M28)) -> 1500 | Q28: =IF($B$5="Solo/Startup", H28, IF($B$5="Small Business", K28, N28)) -> 2500 | R28: =IF($B$6="Low", P28, IF($B$6="High", Q28, AVERAGE(P28,Q28))) -> 2500 | S28: =IF(A28, B28*R28, 0) -> 0 | T28: =IF(F28="Monthly","Monthly","One-time/Non-monthly") -> One-time/Non-monthly
A29: FALSE | B29: 1 | C29: FALSE | D29: Tier 3 – Strategic Growth Consulting (High-End Layer) | E29: Financial Strategy Intensive (90-minute workshop) | F29: Session | G29: 250 | H29: 400 | J29: 400 | K29: 600 | M29: 600 | N29: 900 | P29: =IF($B$5="Solo/Startup", G29, IF($B$5="Small Business", J29, M29)) -> 250 | Q29: =IF($B$5="Solo/Startup", H29, IF($B$5="Small Business", K29, N29)) -> 400 | R29: =IF($B$6="Low", P29, IF($B$6="High", Q29, AVERAGE(P29,Q29))) -> 400 | S29: =IF(A29, B29*R29, 0) -> 0 | T29: =IF(F29="Monthly","Monthly","One-time/Non-monthly") -> One-time/Non-monthly
A31: TOTALS
A32: Monthly Subtotal | B32: =SUMIF(T10:T29,"Monthly",S10:S29) -> 1900
A33: One-time/Non-monthly Subtotal | B33: =SUMIF(T10:T29,"One-time/Non-monthly",S10:S29) -> 5500
A34: Maintenance Add-on (Monthly) | B34: =SUM(U10:U29) -> 0
A35: Grand Total – Month 1 | B35: =B32+B33+B31 -> 7400
A36: Ongoing Monthly Total

Sheet Quote Builder
A1: YOUR LOGO HERE
A5: Proposal For: | B5: Client Name | D5: Client Size: | E5: =Calculator!B5 -> Solo/Startup
A6: Company: | B6: Company Name | D6: Price Point: | E6: =Calculator!B6 -> High
A7: Prepared By: | B7: Your Firm Name
A9: Service | B9: Billing | C9: Qty | D9: Unit Price | E9: Line Total
A10: {=_xlfn._xlws.FILTER(Calculator!E10:E29, Calculator!A10:A29=TRUE)} -> Bookkeeping | B10: {=_xlfn._xlws.FILTER(Calculator!F10:F29, Calculator!A10:A29=TRUE)} -> Monthly | C10: {=_xlfn._xlws.FILTER(Calculator!B10:B29, Calculator!A10:A29=TRUE)} -> 1 | D10: {=_xlfn._xlws.FILTER(Calculator!R10:R29, Calculator!A10:A29=TRUE)} -> 800 | E10: {=_xlfn._xlws.FILTER(Calculator!S10:S29, Calculator!A10:A29=TRUE)} -> 800
A11: Month-end close + Reconciliations + Financial Statement Prep | B11: Monthly | C11: 1 | D11: 800 | E11: 800
A12: Payroll + 1099 contractor setup | B12: Monthly | C12: 1 | D12: 300 | E12: 300
A13: Cleanup Projects or accounting migrations | B13: Project | C13: 1 | D13: 1500 | E13: 1500
A14: Accounting System Overhaul | B14: Project | C14: 1 | D14: 2000 | E14: 2000
A15: KPI Dashboard Design (Power BI, Excel, Power Query) | B15: One-time | C15: 1 | D15: 2000 | E15: 2000
A16: Total | E16: =SUM(_xlfn.ANCHORARRAY(E10)) -> 7400
